cpulimiter/__init__.py
cpulimiter/limiter.py
cpulimiter/limiter_engine.dll
cpulimiter/limiter_legacy.py
cpulimiter/utils.py
cpulimiter-1.0.11.dist-info/licenses/LICENSE
cpulimiter-1.0.11.dist-info/METADATA
cpulimiter-1.0.11.dist-info/WHEEL
cpulimiter-1.0.11.dist-info/top_level.txt
cpulimiter-1.0.11.dist-info/RECORD
